tensorboard_reducer/__init__.py
tensorboard_reducer/event_loader.py
tensorboard_reducer/load.py
tensorboard_reducer/main.py
tensorboard_reducer/reduce.py
tensorboard_reducer/write.py
tensorboard_reducer-0.4.0.dist-info/METADATA
tensorboard_reducer-0.4.0.dist-info/WHEEL
tensorboard_reducer-0.4.0.dist-info/entry_points.txt
tensorboard_reducer-0.4.0.dist-info/top_level.txt
tensorboard_reducer-0.4.0.dist-info/RECORD
