Metadata-Version: 2.4
Name: tensorboard-reducer
Version: 0.4.0
Summary: Reduce multiple TensorBoard runs to new event (or CSV) files
Author-email: Janosh Riebesell <janosh.riebesell@gmail.com>
License: MIT License
Project-URL: Homepage, https://github.com/janosh/tensorboard-reducer
Project-URL: Package, https://pypi.org/project/tensorboard-reducer
Keywords: aggregate,averaging,logs,machine-learning,pytorch,reducer,runs,statistics,tensorboard
Classifier: License :: OSI Approved :: MIT License
Classifier: Programming Language :: Python :: 3 :: Only
Classifier: Programming Language :: Python :: 3
Classifier: Programming Language :: Python :: 3.11
Classifier: Programming Language :: Python :: 3.12
Classifier: Programming Language :: Python :: 3.13
Classifier: Programming Language :: Python :: 3.14
Requires-Python: >=3.11
Requires-Dist: numpy>=1.19
Requires-Dist: pandas>=1.0.0
Requires-Dist: tensorboard>=2.0
Requires-Dist: tqdm>=4.0
Provides-Extra: test
Requires-Dist: pytest; extra == "test"
Requires-Dist: pytest-cov; extra == "test"
Requires-Dist: torch>=1.6; extra == "test"
Provides-Extra: excel
Requires-Dist: openpyxl; extra == "excel"
